{"resourceType":"Immunization","id":"BA00E169-08EB-48A0-9298-C7D576875CC1","meta":{"profile":["http://fhir.nhs.net/StructureDefinition/gpconnect-immunization-1-0"]},"identifier":[{"value":"649E6D92-1083-48A5-AC88-C14D31B836ED"}],"status":"in-progress","date":"2016-03-01","vaccineCode":{"coding":[{"system":"http://snomed.info/sct","code":"400331004","display":"Rabies vaccine 0.25iu/0.1mL powder for injection single dose syringe (product)"}]},"patient":{"reference":"Patient/1A6E1B1C-6340-4663-926C-9CD1306EAAF8","display":"Sally Taylor"},"wasNotGiven":false,"reported":false,"performer":{"reference":"Practitioner/649DE1D2-4938-4DA3-B377-E6F015F37EAF"},"encounter":{"reference":"Encounter/5EBCD865-7D33-42A7-82DC-C2203A5DE0DE"},"lotNumber":"63259874","expirationDate":"2020-01-01","site":{"coding":[{"system":"http://snomed.info/sct","code":"35259002","display":"Structure of deltoid muscle (body structure)"}]},"route":{"coding":[{"system":"http://snomed.info/sct","code":"285837007","display":"Injection into body site (procedure)"}]},"doseQuantity":{"value":0.1,"unit":"mL","system":"http://unitsofmeasure.org","code":"mL"},"vaccinationProtocol":[{"doseSequence":1,"targetDisease":[{"coding":[{"system":"http://snomed.info/sct","code":"14168008","display":"Rabies (disorder)"}]}],"doseStatus":{"coding":[{"system":"http://hl7.org/fhir/vaccination-protocol-dose-status","code":"count","display":"Counts"}]}}]}